{
  "week": "2025-W41",
  "startDate": "2025-10-06",
  "endDate": "2025-10-12",
  "generatedAt": "2026-06-27T15:56:01.637Z",
  "prLevel": {
    "prs": [
      {
        "pr": 106,
        "title": "refactors readiness thermometer, implements it into slide deck",
        "author": "Chris",
        "mergedAt": "2025-10-10T17:34:49Z",
        "additions": 0,
        "customAdditions": 48,
        "deletions": 0,
        "files": 6,
        "points": 3,
        "rationale": "Refactors the readiness thermometer component, extracts shared utility logic, and integrates it into the slide deck across 6 files with 48 custom lines — a modest but meaningful refactor and feature integration.",
        "category": "UI/UX",
        "vendored": false,
        "vendoredRatio": 0,
        "isMultiAuthor": true,
        "attribution": {
          "Chris": 0.6,
          "Jason": 0.4
        }
      },
      {
        "pr": 104,
        "title": "introduces data tables for users and queue, refactors admin check int…",
        "author": "Chris",
        "mergedAt": "2025-10-10T17:02:27Z",
        "additions": 0,
        "customAdditions": 467,
        "deletions": 0,
        "files": 9,
        "points": 8,
        "rationale": "Introduces data tables for users and queue with column definitions, refactors admin auth check into middleware, and adds queue utilities across 9 files with 467 custom lines — a significant admin feature and architectural refactor.",
        "category": "Admin/Tools",
        "vendored": false,
        "vendoredRatio": 0,
        "isMultiAuthor": true,
        "attribution": {
          "Chris": 0.9,
          "Jason": 0.1
        }
      },
      {
        "pr": 108,
        "title": "Staging",
        "author": "Jason",
        "mergedAt": "2025-10-09T03:01:06Z",
        "additions": 0,
        "customAdditions": 61,
        "deletions": 0,
        "files": 4,
        "points": 5,
        "rationale": "Adds or updates server actions for AWS products and monthly spend, updates the AWS product selector component, and touches the readiness page across 4 files with 61 lines — solid feature work spanning data fetching and UI.",
        "category": "Core Platform",
        "vendored": false,
        "vendoredRatio": 0,
        "isMultiAuthor": false,
        "attribution": {
          "Jason": 1
        }
      },
      {
        "pr": 107,
        "title": "Fix onboarding authentication and AWS product fetching",
        "author": "Jason",
        "mergedAt": "2025-10-09T02:38:26Z",
        "additions": 0,
        "customAdditions": 61,
        "deletions": 0,
        "files": 4,
        "points": 5,
        "rationale": "Fixes onboarding authentication flow and AWS product fetching across the same 4 files as PR #108 with 61 custom lines, indicating meaningful bug fixes touching auth, server actions, and a UI selector component.",
        "category": "Core Platform",
        "vendored": false,
        "vendoredRatio": 0,
        "isMultiAuthor": false,
        "attribution": {
          "Jason": 1
        }
      },
      {
        "pr": 103,
        "title": "Improve DOMPurify loading and error handling",
        "author": "Jason",
        "mergedAt": "2025-10-08T07:51:57Z",
        "additions": 0,
        "customAdditions": 10,
        "deletions": 0,
        "files": 1,
        "points": 2,
        "rationale": "Small improvement to DOMPurify loading and error handling in a single component with only 10 custom lines — a minor defensive fix.",
        "category": "Core Platform",
        "vendored": false,
        "vendoredRatio": 0,
        "isMultiAuthor": false,
        "attribution": {
          "Jason": 1
        }
      },
      {
        "pr": 102,
        "title": "Debugging progress",
        "author": "Jason",
        "mergedAt": "2025-10-08T07:38:07Z",
        "additions": 0,
        "customAdditions": 4,
        "deletions": 0,
        "files": 1,
        "points": 1,
        "rationale": "Only 4 lines changed in a single file as a debugging pass — trivial change.",
        "category": "Core Platform",
        "vendored": false,
        "vendoredRatio": 0,
        "isMultiAuthor": false,
        "attribution": {
          "Jason": 1
        }
      },
      {
        "pr": 101,
        "title": "Improve companyId handling and add admin test page",
        "author": "Jason",
        "mergedAt": "2025-10-08T06:47:55Z",
        "additions": 0,
        "customAdditions": 60,
        "deletions": 0,
        "files": 3,
        "points": 3,
        "rationale": "Improves companyId handling in the DAL, updates the AI readiness entrypoint, and adds an admin test page across 3 files with 60 custom lines — a small but meaningful multi-layer improvement.",
        "category": "Admin/Tools",
        "vendored": false,
        "vendoredRatio": 0,
        "isMultiAuthor": false,
        "attribution": {
          "Jason": 1
        }
      },
      {
        "pr": 100,
        "title": "Debugging progress",
        "author": "Jason",
        "mergedAt": "2025-10-08T06:14:02Z",
        "additions": 0,
        "customAdditions": 140,
        "deletions": 0,
        "files": 5,
        "points": 5,
        "rationale": "Debugging work spanning 5 files including the AI entrypoint, queue action, worker, and a new admin readiness-logs page with 140 custom lines — meaningful cross-cutting diagnostic and observability additions.",
        "category": "AI/Agents",
        "vendored": false,
        "vendoredRatio": 0,
        "isMultiAuthor": false,
        "attribution": {
          "Jason": 1
        }
      },
      {
        "pr": 99,
        "title": "Update entrypoint and apprunner config for migrations",
        "author": "Jason",
        "mergedAt": "2025-10-08T03:51:27Z",
        "additions": 0,
        "customAdditions": 8,
        "deletions": 0,
        "files": 2,
        "points": 2,
        "rationale": "Small infrastructure update adding migration support to the entrypoint script and App Runner config across 2 files with 8 lines.",
        "category": "DevOps",
        "vendored": false,
        "vendoredRatio": 0,
        "isMultiAuthor": false,
        "attribution": {
          "Jason": 1
        }
      },
      {
        "pr": 98,
        "title": "Update build order and add DATABASE_URL secret",
        "author": "Jason",
        "mergedAt": "2025-10-08T03:45:32Z",
        "additions": 0,
        "customAdditions": 4,
        "deletions": 0,
        "files": 1,
        "points": 1,
        "rationale": "Trivial App Runner config tweak adding a DATABASE_URL secret with only 4 lines in one file.",
        "category": "DevOps",
        "vendored": false,
        "vendoredRatio": 0,
        "isMultiAuthor": false,
        "attribution": {
          "Jason": 1
        }
      },
      {
        "pr": 97,
        "title": "Update apprunner.yaml build and run configuration",
        "author": "Jason",
        "mergedAt": "2025-10-08T03:34:21Z",
        "additions": 0,
        "customAdditions": 7,
        "deletions": 0,
        "files": 1,
        "points": 1,
        "rationale": "Minor App Runner build/run configuration update with 7 lines in a single YAML file.",
        "category": "DevOps",
        "vendored": false,
        "vendoredRatio": 0,
        "isMultiAuthor": false,
        "attribution": {
          "Jason": 1
        }
      },
      {
        "pr": 96,
        "title": "Update apprunner.yaml",
        "author": "Jason",
        "mergedAt": "2025-10-08T03:29:55Z",
        "additions": 0,
        "customAdditions": 9,
        "deletions": 0,
        "files": 1,
        "points": 1,
        "rationale": "Small App Runner YAML update with 9 lines in one file — a config tweak.",
        "category": "DevOps",
        "vendored": false,
        "vendoredRatio": 0,
        "isMultiAuthor": false,
        "attribution": {
          "Jason": 1
        }
      },
      {
        "pr": 95,
        "title": "Staging",
        "author": "Jason",
        "mergedAt": "2025-10-08T03:11:06Z",
        "additions": 0,
        "customAdditions": 2,
        "deletions": 0,
        "files": 1,
        "points": 1,
        "rationale": "Trivial 2-line change to apprunner.yaml.",
        "category": "DevOps",
        "vendored": false,
        "vendoredRatio": 0,
        "isMultiAuthor": false,
        "attribution": {
          "Jason": 1
        }
      },
      {
        "pr": 94,
        "title": "Add error handling for analytics and editor actions",
        "author": "Jason",
        "mergedAt": "2025-10-08T01:49:39Z",
        "additions": 0,
        "customAdditions": 20,
        "deletions": 0,
        "files": 4,
        "points": 2,
        "rationale": "Adds error handling across 4 files (analytics, editor, slide deck client, middleware) with only 20 custom lines — small defensive improvements.",
        "category": "Core Platform",
        "vendored": false,
        "vendoredRatio": 0,
        "isMultiAuthor": false,
        "attribution": {
          "Jason": 1
        }
      },
      {
        "pr": 93,
        "title": "Major Feature Release: Task Management, Admin Enhancements, and Audit System",
        "author": "Jason",
        "mergedAt": "2025-10-08T01:15:21Z",
        "additions": 0,
        "customAdditions": 4693,
        "deletions": 0,
        "files": 69,
        "points": 21,
        "rationale": "A transformative release spanning 69 files and 4693 custom lines covering a full task management system with drag-and-drop hierarchy, an audit/event system, admin enhancements, auth flows (password reset, email verify), schema changes, and multi-week contributions from two engineers.",
        "category": "Core Platform",
        "vendored": false,
        "vendoredRatio": 5,
        "isMultiAuthor": true,
        "attribution": {
          "Jason": 0.65,
          "Chris": 0.35
        }
      },
      {
        "pr": 91,
        "title": "Ch/audit table",
        "author": "Chris",
        "mergedAt": "2025-10-07T23:51:32Z",
        "additions": 0,
        "customAdditions": 1531,
        "deletions": 0,
        "files": 36,
        "points": 13,
        "rationale": "1531 custom lines across 36 files spanning schema changes, new audit event tracking infrastructure, multiple public-facing pages, admin views, and cross-cutting concerns represents a major feature with architectural implications.",
        "category": "Core Platform",
        "vendored": false,
        "vendoredRatio": 4,
        "isMultiAuthor": false,
        "attribution": {
          "Chris": 1
        }
      },
      {
        "pr": 92,
        "title": "Admin User Management: Password & Role Controls",
        "author": "Jason",
        "mergedAt": "2025-10-07T23:29:08Z",
        "additions": 0,
        "customAdditions": 616,
        "deletions": 0,
        "files": 4,
        "points": 5,
        "rationale": "616 lines across 4 files adding password change and role management dialogs with corresponding admin actions is a solid, self-contained admin feature with meaningful UI and backend work.",
        "category": "Admin/Tools",
        "vendored": false,
        "vendoredRatio": 0,
        "isMultiAuthor": false,
        "attribution": {
          "Jason": 1
        }
      }
    ],
    "totalPoints": 79,
    "byAuthor": {
      "Chris": 29.4,
      "Jason": 49.7
    },
    "byCategory": {
      "UI/UX": 3,
      "Admin/Tools": 16,
      "Core Platform": 49,
      "AI/Agents": 5,
      "DevOps": 6
    }
  },
  "grouped": {
    "stories": [
      {
        "id": 1,
        "name": "Staging Environment Deployment & Stabilization",
        "points": 21,
        "category": "DevOps",
        "prs": [
          95,
          96,
          97,
          98,
          99,
          108
        ],
        "rationale": "Iteratively configured and stabilized the staging environment including AppRunner setup, build order, database secrets, migration entrypoints, and final staging deployment."
      },
      {
        "id": 2,
        "name": "Task Management, Audit System & Admin Enhancements",
        "points": 21,
        "category": "Core Platform",
        "prs": [
          93,
          91
        ],
        "rationale": "Delivered a major feature release combining task management, an audit table/system, and admin enhancements to give teams visibility and control over platform activity."
      },
      {
        "id": 3,
        "name": "Onboarding Authentication & AWS Product Integration Fix",
        "points": 5,
        "category": "Core Platform",
        "prs": [
          107
        ],
        "rationale": "Resolved broken onboarding authentication flow and fixed AWS product fetching to ensure new users can successfully complete sign-up and access their products."
      },
      {
        "id": 4,
        "name": "Platform Stability & Error Handling Improvements",
        "points": 5,
        "category": "Core Platform",
        "prs": [
          94,
          103,
          102
        ],
        "rationale": "Improved overall platform resilience by adding error handling for analytics and editor actions, fixing DOMPurify loading issues, and resolving miscellaneous bugs surfaced during debugging."
      },
      {
        "id": 5,
        "name": "Admin User & Queue Management Dashboard",
        "points": 13,
        "category": "Admin/Tools",
        "prs": [
          104,
          92,
          101
        ],
        "rationale": "Built out a comprehensive admin experience including data tables for users and queue management, password and role controls, and improved company ID handling with a dedicated admin test page."
      },
      {
        "id": 6,
        "name": "Business Readiness Score Visual & Slide Deck Integration",
        "points": 3,
        "category": "UI/UX",
        "prs": [
          106
        ],
        "rationale": "Refactored the readiness thermometer component and embedded it into the slide deck to give stakeholders a clear visual representation of business readiness."
      },
      {
        "id": 7,
        "name": "AI Agent Debugging & Progress Tracking",
        "points": 5,
        "category": "AI/Agents",
        "prs": [
          100
        ],
        "rationale": "Advanced debugging efforts on AI agent workflows to identify and address progress-blocking issues in the agent pipeline."
      }
    ],
    "totalPoints": 73,
    "byAuthor": {
      "Jason": 55.5,
      "Chris": 17.5
    }
  },
  "meta": {
    "teamSize": 1.8,
    "codingAllocation": 0.8,
    "fteEquiv": {
      "prLevel": 18.24,
      "grouped": 16.86
    },
    "ptsPerWeekPerFTE": 4.33
  }
}